psychopy_usbToBNC/__init__.py
psychopy_usbToBNC/usbToBNC/__init__.py
psychopy_usbToBNC/usbToBNC/classic/eau.png
psychopy_usbToBNC/usbToBNC/classic/reward.png
psychopy_usbToBNC/usbToBNC/classic/reward@2x.png
psychopy_usbToBNC/usbToBNC/dark/eau.png
psychopy_usbToBNC/usbToBNC/dark/reward.png
psychopy_usbToBNC/usbToBNC/dark/reward@2x.png
psychopy_usbToBNC/usbToBNC/light/eau.png
psychopy_usbToBNC/usbToBNC/light/reward.png
psychopy_usbToBNC/usbToBNC/light/reward@2x.png
psychopy_usbToBNC-0.0.6.dist-info/LICENSE
psychopy_usbToBNC-0.0.6.dist-info/METADATA
psychopy_usbToBNC-0.0.6.dist-info/WHEEL
psychopy_usbToBNC-0.0.6.dist-info/entry_points.txt
psychopy_usbToBNC-0.0.6.dist-info/top_level.txt
psychopy_usbToBNC-0.0.6.dist-info/RECORD
